calc-joao-lcareis/__init__.py
calc-joao-lcareis/file1_name.py
calculadora/__init__.py
calculadora/file1_name.py
calc_joao_lcareis-0.0.1.dist-info/METADATA
calc_joao_lcareis-0.0.1.dist-info/WHEEL
calc_joao_lcareis-0.0.1.dist-info/top_level.txt
calc_joao_lcareis-0.0.1.dist-info/RECORD
