Metadata-Version: 2.1
Name: calc-joao-lcareis
Version: 0.0.1
Summary: Mini Calculadora
Home-page: https://github.com/JoaoLucio1204/Pacotes
Author: JoaoLucio
Requires-Python: >=3.8
